start_compiler/__init__.py
start_compiler/compile.py
start_compiler/import_start.py
start_compiler/start_grammar.ebnf
start_compiler/starttypes.py
start_compiler-2.0.1.0.dist-info/licenses/LICENSE
start_compiler-2.0.1.0.dist-info/METADATA
start_compiler-2.0.1.0.dist-info/WHEEL
start_compiler-2.0.1.0.dist-info/top_level.txt
start_compiler-2.0.1.0.dist-info/RECORD
