Metadata-Version: 2.4
Name: start_compiler
Version: 2.0.1.0
Summary: A package to compile the langauge START
Home-page: https://github.com/jjgsherwood/start_compiler
Author: Joost Broekens; Jonne Goedhart
Author-email: Joost.broekens@gmail.com
License: Creative Commons CC BY-NC-SA 4.0
Classifier: Programming Language :: Python :: 3
Classifier: Operating System :: OS Independent
Requires-Python: >=3.10
License-File: LICENSE
Requires-Dist: lark>=1.1.2
Requires-Dist: numpy>=1.26.4
Requires-Dist: pynput>=1.8.1
Dynamic: author
Dynamic: author-email
Dynamic: classifier
Dynamic: description
Dynamic: description-content-type
Dynamic: home-page
Dynamic: license
Dynamic: license-file
Dynamic: requires-dist
Dynamic: requires-python
Dynamic: summary
